hoursofoperation/__init__.py
hoursofoperation/_version.py
hoursofoperation/lib.py
hoursofoperation/test/__init__.py
hoursofoperation/test/test_lib.py
hoursofoperation-0.1.12.dist-info/LICENSE
hoursofoperation-0.1.12.dist-info/METADATA
hoursofoperation-0.1.12.dist-info/WHEEL
hoursofoperation-0.1.12.dist-info/top_level.txt
hoursofoperation-0.1.12.dist-info/RECORD
