Metadata-Version: 2.1
Name: hoursofoperation
Version: 0.1.12
Summary: Utilities for loading and doing calculations with a partner's hours of operations configration.
Home-page: https://github.com/Brightmd/hoursofoperation
Author: Ashley Fisher
Author-email: fish.ash@gmail.com
License: UNKNOWN
Keywords: hours
Platform: UNKNOWN
Requires-Dist: codado
Requires-Dist: python-dateutil
Requires-Dist: pytz
Provides-Extra: dev
Requires-Dist: pytest ; extra == 'dev'
Requires-Dist: pytest-coverage ; extra == 'dev'
Requires-Dist: pytest-flakes ; extra == 'dev'
Requires-Dist: tox ; extra == 'dev'
Requires-Dist: wheel ; extra == 'dev'
